UART_UVM/receiver.v
module receiver (rx,clk,clk_en,reset,ready,dout);
    input rx;
    input clk;
    input clk_en;
    input reset;
    output reg ready;
    output reg [7:0]dout;

    
    parameter RX_STATE_START	= 2'b00;
    parameter RX_STATE_DATA		= 2'b01;
    parameter RX_STATE_STOP		= 2'b10;

    reg [1:0] state     = RX_STATE_START; 
    reg [3:0] sample    = 0;
    reg [3:0] bit_pos   = 0;
    reg [7:0] op_reg    = 0;


    always @(posedge clk) 
    begin
        if(reset)   ready <= 0;

        if(clk_en)
        begin
            case (state)
                RX_STATE_START : 
                    begin
                        ready <= 0;
                        if(!rx || sample != 0) 
                            sample <= sample + 4'b1;

                        if(sample == 15)
                        begin
                            state   <= RX_STATE_DATA;
                            bit_pos <= 0;
                            sample  <= 0;
                            op_reg  <= 0;
                        end
                    end
                RX_STATE_DATA  : 
                    begin
                        sample <= sample + 4'b1;
                        if(sample == 4'h8)
                        begin
                            op_reg[bit_pos[2:0]] <= rx;
                            bit_pos <= bit_pos + 4'b1;
                        end
                        if(bit_pos == 8 && sample == 15)    state <= RX_STATE_STOP;
                    end
                RX_STATE_STOP  : 
                    begin
                        if(sample == 15 || (sample >= 8 && !rx))
                        begin
                            state  <= RX_STATE_START;
                            ready  <= 1;
                            dout   <= op_reg;
				            sample <= 0;
                        end
                        else    sample <= sample + 4'b1;
                    end
                default: 
                    begin
                        state <= RX_STATE_START;
                    end
            endcase
        end
    end

endmodule

Design_UART/transmitter.v
module transmitter (din,wr_en,clk,clk_en,tx,tx_busy);
    input [7:0] din;
    input wr_en;
    input clk;
    input clk_en;
    output reg tx;
    output tx_busy;
    
    initial 
    begin
	 tx = 1'b1;
    end
    
parameter STATE_IDLE	= 2'b00;
parameter STATE_START	= 2'b01;
parameter STATE_DATA	= 2'b10;
parameter STATE_STOP	= 2'b11;

    reg [7:0] data      = 8'h00;
    reg [2:0] bit_pos   = 3'h0;
    reg [1:0] state     = STATE_IDLE;

    always @(posedge clk ) 
    begin
        case (state)
            STATE_IDLE: 
            begin
                if (wr_en) 
                begin
                    state <= STATE_START;
                    data<=din;
                    bit_pos<=3'h0;
                end                 
            end
            STATE_START:
            begin
                if (clk_en) 
                begin
                    tx<=1'b0;
                    state<=STATE_DATA;
                end              
            end
            STATE_DATA:
            begin
                if (clk_en) 
                begin
                    if(bit_pos==3'h7)
                        state<=STATE_STOP;
                    else
                        bit_pos <= bit_pos + 3'h1;
                    tx<=data[bit_pos];    
                end
            end
            STATE_STOP:
            begin
                if (clk_en) 
                begin
                    tx<=1'b1;
                    state<=STATE_IDLE;    
                end
            end
            default: 
            begin
                tx<=1'b1;
                state<=STATE_IDLE;    
            end
        endcase   
    end
assign tx_busy=(state!=STATE_IDLE);
endmodule

Design_UART/baud.v
module baud (clk,rx_en,tx_en);
    input clk;
    output rx_en,tx_en;
    
    parameter RX_MAX   = 50000000/(115200*16);    
    parameter TX_MAX   = 50000000/115200;    
    parameter RX_WIDTH = $clog2(RX_MAX);
    parameter TX_WIDTH = $clog2(TX_MAX);
    reg [RX_WIDTH-1:0] rx_acc = 0;
    reg [TX_WIDTH-1:0] tx_acc = 0;

    assign rx_en = (rx_acc == 5'd0);
    assign tx_en = (tx_acc == 9'd0);

    always @(posedge clk)
    begin
        if(rx_acc == RX_MAX[RX_WIDTH-1:0])  rx_acc <= 0;
        else                                rx_acc <= rx_acc + 1;
    end
    
    always @(posedge clk)
    begin
        if(tx_acc == TX_MAX[TX_WIDTH-1:0])  tx_acc <= 0;
        else                                tx_acc <= tx_acc + 1;
    end

endmodule

UART with parity/uart.v
module uart(input wire [7:0] din,
	    input wire wr_en,
	    input wire clk,
	    output wire tx_busy,
	    output wire ready,
	    input wire reset,
	    output wire [7:0] dout);

wire rx_en, tx_en, tx_rx;

baud uart_baud(.clk(clk),
			.rx_en(rx_en),
			.tx_en(tx_en));

transmitter uart_tx(.din(din),
		    .wr_en(wr_en),
		    .clk(clk),
		    .clk_en(tx_en),
		    .tx(tx_rx),
		    .tx_busy(tx_busy));

receiver uart_rx(.rx(tx_rx),
		 	.ready(ready),
		 	.reset(reset),
		 	.clk(clk),
		 	.clk_en(rx_en),
		 	.dout(dout));

endmodule

Design_UART/testbench.v
// `include "uart.v"
module uart_tx_test();

    reg [7:0] din = 0;
    reg clk = 0;
    reg wr_en = 0;
    
    wire tx_busy;
    wire ready;
    wire [7:0] dout;
    
    reg reset = 0;
    
    uart test_uart(.din(din),
                   .wr_en(wr_en),
                   .clk(clk),
                   .tx_busy(tx_busy),
                   .ready(ready),
                   .reset(reset),
                   .dout(dout));
   
    initial begin
        $dumpfile("uart.vcd");
        $dumpvars(0, uart_tx_test);
        wr_en <= 1'b1;
        #2 wr_en <= 1'b0;
    end
    
    always 
    begin
        #1 clk = ~clk;
    end
    
    // always @(posedge ready) begin
    //     #2 reset <= 1;
    //     #2 reset <= 0;
    //     if (dout != din) begin
    //         repeat(10)@(posedge clk);
    //         $display("FAIL: dout %x does not match din %x @ time = %0t", dout, din,$time);
    //         $finish;
    //     end else begin
    //         if (dout == 8'hff) begin
    //             $display("SUCCESS: all bytes verified");
    //             $finish;
    //         end
    //         din <= din + 1'b1;
    //         wr_en <= 1'b1;
    //         #2 wr_en <= 1'b0;
    //     end
    // end

    initial begin
        @(posedge ready)
        #2 reset <= 1;
        #2 reset <= 0;
        if (dout != din) begin
            repeat(10)@(posedge clk);
            $display("FAIL: dout %x does not match din %x @ time = %0t", dout, din,$time);
            $finish;
        end 
        else begin
            if (dout == 8'hff) begin
                $display("SUCCESS: all bytes verified");
                $finish;
            end
            din <= 8'b11001110;
            wr_en <= 1'b1;
            #2 wr_en <= 1'b0;
            repeat(20000)@(posedge clk);
        end
            $finish;
    end
    
    endmodule

Design_UART/uart.vcd
$date
	Sun May 01 23:00:41 2022
$end
$version
	QuestaSim Version 10.7c
$end
$timescale
	1ns
$end

$scope module uart_tx_test $end
$var reg 8 ! din [7:0] $end
$var reg 1 " clk $end
$var reg 1 # wr_en $end
$var wire 1 $ tx_busy $end
$var wire 1 % ready $end
$var wire 1 & dout [7] $end
$var wire 1 ' dout [6] $end
$var wire 1 ( dout [5] $end
$var wire 1 ) dout [4] $end
$var wire 1 * dout [3] $end
$var wire 1 + dout [2] $end
$var wire 1 , dout [1] $end
$var wire 1 - dout [0] $end
$var reg 1 . reset $end

$scope module test_uart $end
$var wire 1 / din [7] $end
$var wire 1 0 din [6] $end
$var wire 1 1 din [5] $end
$var wire 1 2 din [4] $end
$var wire 1 3 din [3] $end
$var wire 1 4 din [2] $end
$var wire 1 5 din [1] $end
$var wire 1 6 din [0] $end
$var wire 1 7 wr_en $end
$var wire 1 8 clk $end
$var wire 1 $ tx_busy $end
$var wire 1 % ready $end
$var wire 1 9 reset $end
$var wire 1 & dout [7] $end
$var wire 1 ' dout [6] $end
$var wire 1 ( dout [5] $end
$var wire 1 ) dout [4] $end
$var wire 1 * dout [3] $end
$var wire 1 + dout [2] $end
$var wire 1 , dout [1] $end
$var wire 1 - dout [0] $end
$var wire 1 : rx_en $end
$var wire 1 ; tx_en $end
$var wire 1 < tx_rx $end

$scope module uart_baud $end
$var parameter 32 = RX_MAX $end
$var parameter 32 > TX_MAX $end
$var parameter 32 ? RX_WIDTH $end
$var parameter 32 @ TX_WIDTH $end
$var wire 1 8 clk $end
$var wire 1 : rx_en $end
$var wire 1 ; tx_en $end
$var reg 5 A rx_acc [4:0] $end
$var reg 9 B tx_acc [8:0] $end
$upscope $end

$scope module uart_tx $end
$var parameter 2 C STATE_IDLE $end
$var parameter 2 D STATE_START $end
$var parameter 2 E STATE_DATA $end
$var parameter 2 F STATE_STOP $end
$var wire 1 / din [7] $end
$var wire 1 0 din [6] $end
$var wire 1 1 din [5] $end
$var wire 1 2 din [4] $end
$var wire 1 3 din [3] $end
$var wire 1 4 din [2] $end
$var wire 1 5 din [1] $end
$var wire 1 6 din [0] $end
$var wire 1 7 wr_en $end
$var wire 1 8 clk $end
$var wire 1 ; clk_en $end
$var reg 1 G tx $end
$var wire 1 $ tx_busy $end
$var reg 8 H data [7:0] $end
$var reg 3 I bit_pos [2:0] $end
$var reg 2 J state [1:0] $end
$upscope $end

$scope module uart_rx $end
$var parameter 2 K RX_STATE_START $end
$var parameter 2 L RX_STATE_DATA $end
$var parameter 2 M RX_STATE_STOP $end
$var wire 1 < rx $end
$var wire 1 8 clk $end
$var wire 1 : clk_en $end
$var wire 1 9 reset $end
$var reg 1 N ready $end
$var reg 8 O dout [7:0] $end
$var reg 2 P state [1:0] $end
$var reg 4 Q sample [3:0] $end
$var reg 4 R bit_pos [3:0] $end
$var reg 8 S op_reg [7:0] $end
$upscope $end
$upscope $end
$upscope $end
$enddefinitions $end
#0
$dumpvars
b0 !
0"
1#
0.
b0 A
b0 B
1G
b0 H
b0 I
b0 J
0N
b0 O
b0 P
b0 Q
b0 R
b0 S
b11011 =
b110110010 >
b101 ?
b1001 @
b0 C
b1 D
b10 E
b11 F
b0 K
b1 L
b10 M
0$
0%
0-
0,
0+
0*
0)
0(
0'
0&
1:
1;
1<
09
08
17
06
05
04
03
02
01
00
0/
$end
#1
1"
18
b1 A
b1 B
b1 J
0:
0;
1$
#2
0"
08
0#
07
#3
1"
18
b10 A
b10 B
#4
0"
08
#5
1"
18
b11 A
b11 B
#6
0"
08
#7
1"
18
b100 A
b100 B
#8
0"
08
#9
1"
18
b101 A
b101 B
#10
0"
08
#11
1"
18
b110 A
b110 B
#12
0"
08
#13
1"
18
b111 A
b111 B
#14
0"
08
#15
1"
18
b1000 A
b1000 B
#16
0"
08
#17
1"
18
b1001 A
b1001 B
#18
0"
08
#19
1"
18
b1010 A
b1010 B
#20
0"
08
#21
1"
18
b1011 A
b1011 B
#22
0"
08
#23
1"
18
b1100 A
b1100 B
#24
0"
08
#25
1"
18
b1101 A
b1101 B
#26
0"
08
#27
1"
18
b1110 A
b1110 B
#28
0"
08
#29
1"
18
b1111 A
b1111 B
#30
0"
08
#31
1"
18
b10000 A
b10000 B
#32
0"
08
#33
1"
18
b10001 A
b10001 B
#34
0"
08
#35
1"
18
b10010 A
b10010 B
#36
0"
08
#37
1"
18
b10011 A
b10011 B
#38
0"
08
#39
1"
18
b10100 A
b10100 B
#40
0"
08
#41
1"
18
b10101 A
b10101 B
#42
0"
08
#43
1"
18
b10110 A
b10110 B
#44
0"
08
#45
1"
18
b10111 A
b10111 B
#46
0"
08
#47
1"
18
b11000 A
b11000 B
#48
0"
08
#49
1"
18
b11001 A
b11001 B
#50
0"
08
#51
1"
18
b11010 A
b11010 B
#52
0"
08
#53
1"
18
b11011 A
b11011 B
#54
0"
08
#55
1"
18
b0 A
b11100 B
1:
#56
0"
08
#57
1"
18
b1 A
b11101 B
0:
#58
0"
08
#59
1"
18
b10 A
b11110 B
#60
0"
08
#61
1"
18
b11 A
b11111 B
#62
0"
08
#63
1"
18
b100 A
b100000 B
#64
0"
08
#65
1"
18
b101 A
b100001 B
#66
0"
08
#67
1"
18
b110 A
b100010 B
#68
0"
08
#69
1"
18
b111 A
b100011 B
#70
0"
08
#71
1"
18
b1000 A
b100100 B
#72
0"
08
#73
1"
18
b1001 A
b100101 B
#74
0"
08
#75
1"
18
b1010 A
b100110 B
#76
0"
08
#77
1"
18
b1011 A
b100111 B
#78
0"
08
#79
1"
18
b1100 A
b101000 B
#80
0"
08
#81
1"
18
b1101 A
b101001 B
#82
0"
08
#83
1"
18
b1110 A
b101010 B
#84
0"
08
#85
1"
18
b1111 A
b101011 B
#86
0"
08
#87
1"
18
b10000 A
b101100 B
#88
0"
08
#89
1"
18
b10001 A
b101101 B
#90
0"
08
#91
1"
18
b10010 A
b101110 B
#92
0"
08
#93
1"
18
b10011 A
b101111 B
#94
0"
08
#95
1"
18
b10100 A
b110000 B
#96
0"
08
#97
1"
18
b10101 A
b110001 B
#98
0"
08
#99
1"
18
b10110 A
b110010 B
#100
0"
08
#101
1"
18
b10111 A
b110011 B
#102
0"
08
#103
1"
18
b11000 A
b110100 B
#104
0"
08
#105
1"
18
b11001 A
b110101 B
#106
0"
08
#107
1"
18
b11010 A
b110110 B
#108
0"
08
#109
1"
18
b11011 A
b110111 B
#110
0"
08
#111
1"
18
b0 A
b111000 B
1:
#112
0"
08
#113
1"
18
b1 A
b111001 B
0:
#114
0"
08
#115
1"
18
b10 A
b111010 B
#116
0"
08
#117
1"
18
b11 A
b111011 B
#118
0"
08
#119
1"
18
b100 A
b111100 B
#120
0"
08
#121
1"
18
b101 A
b111101 B
#122
0"
08
#123
1"
18
b110 A
b111110 B
#124
0"
08
#125
1"
18
b111 A
b111111 B
#126
0"
08
#127
1"
18
b1000 A
b1000000 B
#128
0"
08
#129
1"
18
b1001 A
b1000001 B
#130
0"
08
#131
1"
18
b1010 A
b1000010 B
#132
0"
08
#133
1"
18
b1011 A
b1000011 B
#134
0"
08
#135
1"
18
b1100 A
b1000100 B
#136
0"
08
#137
1"
18
b1101 A
b1000101 B
#138
0"
08
#139
1"
18
b1110 A
b1000110 B
#140
0"
08
#141
1"
18
b1111 A
b1000111 B
#142
0"
08
#143
1"
18
b10000 A
b1001000 B
#144
0"
08
#145
1"
18
b10001 A
b1001001 B
#146
0"
08
#147
1"
18
b10010 A
b1001010 B
#148
0"
08
#149
1"
18
b10011 A
b1001011 B
#150
0"
08
#151
1"
18
b10100 A
b1001100 B
#152
0"
08
#153
1"
18
b10101 A
b1001101 B
#154
0"
08
#155
1"
18
b10110 A
b1001110 B
#156
0"
08
#157
1"
18
b10111 A
b1001111 B
#158
0"
08
#159
1"
18
b11000 A
b1010000 B
#160
0"
08
#161
1"
18
b11001 A
b1010001 B
#162
0"
08
#163
1"
18
b11010 A
b1010010 B
#164
0"
08
#165
1"
18
b11011 A
b1010011 B
#166
0"
08
#167
1"
18
b0 A
b1010100 B
1:
#168
0"
08
#169
1"
18
b1 A
b1010101 B
0:
#170
0"
08
#171
1"
18
b10 A
b1010110 B
#172
0"
08
#173
1"
18
b11 A
b1010111 B
#174
0"
08
#175
1"
18
b100 A
b1011000 B
#176
0"
08
#177
1"
18
b101 A
b1011001 B
#178
0"
08
#179
1"
18
b110 A
b1011010 B
#180
0"
08
#181
1"
18
b111 A
b1011011 B
#182
0"
08
#183
1"
18
b1000 A
b1011100 B
#184
0"
08
#185
1"
18
b1001 A
b1011101 B
#186
0"
08
#187
1"
18
b1010 A
b1011110 B
#188
0"
08
#189
1"
18
b1011 A
b1011111 B
#190
0"
08
#191
1"
18
b1100 A
b1100000 B
#192
0"
08
#193
1"
18
b1101 A
b1100001 B
#194
0"
08
#195
1"
18
b1110 A
b1100010 B
#196
0"
08
#197
1"
18
b1111 A
b1100011 B
#198
0"
08
#199
1"
18
b10000 A
b1100100 B
#200
0"
08
#201
1"
18
b10001 A
b1100101 B
#202
0"
08
#203
1"
18
b10010 A
b1100110 B
#204
0"
08
#205
1"
18
b10011 A
b1100111 B
#206
0"
08
#207
1"
18
b10100 A
b1101000 B
#208
0"
08
#209
1"
18
b10101 A
b1101001 B
#210
0"
08
#211
1"
18
b10110 A
b1101010 B
#212
0"
08
#213
1"
18
b10111 A
b1101011 B
#214
0"
08
#215
1"
18
b11000 A
b1101100 B
#216
0"
08
#217
1"
18
b11001 A
b1101101 B
#218
0"
08
#219
1"
18
b11010 A
b1101110 B
#220
0"
08
#221
1"
18
b11011 A
b1101111 B
#222
0"
08
#223
1"
18
b0 A
b1110000 B
1:
#224
0"
08
#225
1"
18
b1 A
b1110001 B
0:
#226
0"
08
#227
1"
18
b10 A
b1110010 B
#228
0"
08
#229
1"
18
b11 A
b1110011 B
#230
0"
08
#231
1"
18
b100 A
b1110100 B
#232
0"
08
#233
1"
18
b101 A
b1110101 B
#234
0"
08
#235
1"
18
b110 A
b1110110 B
#236
0"
08
#237
1"
18
b111 A
b1110111 B
#238
0"
08
#239
1"
18
b1000 A
b1111000 B
#240
0"
08
#241
1"
18
b1001 A
b1111001 B
#242
0"
08
#243
1"
18
b1010 A
b1111010 B
#244
0"
08
#245
1"
18
b1011 A
b1111011 B
#246
0"
08
#247
1"
18
b1100 A
b1111100 B
#248
0"
08
#249
1"
18
b1101 A
b1111101 B
#250
0"
08
#251
1"
18
b1110 A
b1111110 B
#252
0"
08
#253
1"
18
b1111 A
b1111111 B
#254
0"
08
#255
1"
18
b10000 A
b10000000 B
#256
0"
08
#257
1"
18
b10001 A
b10000001 B
#258
0"
08
#259
1"
18
b10010 A
b10000010 B
#260
0"
08
#261
1"
18
b10011 A
b10000011 B
#262
0"
08
#263
1"
18
b10100 A
b10000100 B
#264
0"
08
#265
1"
18
b10101 A
b10000101 B
#266
0"
08
#267
1"
18
b10110 A
b10000110 B
#268
0"
08
#269
1"
18
b10111 A
b10000111 B
#270
0"
08
#271
1"
18
b11000 A
b10001000 B
#272
0"
08
#273
1"
18
b11001 A
b10001001 B
#274
0"
08
#275
1"
18
b11010 A
b10001010 B
#276
0"
08
#277
1"
18
b11011 A
b10001011 B
#278
0"
08
#279
1"
18
b0 A
b10001100 B
1:
#280
0"
08
#281
1"
18
b1 A
b10001101 B
0:
#282
0"
08
#283
1"
18
b10 A
b10001110 B
#284
0"
08
#285
1"
18
b11 A
b10001111 B
#286
0"
08
#287
1"
18
b100 A
b10010000 B
#288
0"
08
#289
1"
18
b101 A
b10010001 B
#290
0"
08
#291
1"
18
b110 A
b10010010 B
#292
0"
08
#293
1"
18
b111 A
b10010011 B
#294
0"
08
#295
1"
18
b1000 A
b10010100 B
#296
0"
08
#297
1"
18
b1001 A
b10010101 B
#298
0"
08
#299
1"
18
b1010 A
b10010110 B
#300
0"
08
#301
1"
18
b1011 A
b10010111 B
#302
0"
08
#303
1"
18
b1100 A
b10011000 B
#304
0"
08
#305
1"
18
b1101 A
b10011001 B
#306
0"
08
#307
1"
18
b1110 A
b10011010 B
#308
0"
08
#309
1"
18
b1111 A
b10011011 B
#310
0"
08
#311
1"
18
b10000 A
b10011100 B
#312
0"
08
#313
1"
18
b10001 A
b10011101 B
#314
0"
08
#315
1"
18
b10010 A
b10011110 B
#316
0"
08
#317
1"
18
b10011 A
b10011111 B
#318
0"
08
#319
1"
18
b10100 A
b10100000 B
#320
0"
08
#321
1"
18
b10101 A
b10100001 B
#322
0"
08
#323
1"
18
b10110 A
b10100010 B
#324
0"
08
#325
1"
18
b10111 A
b10100011 B
#326
0"
08
#327
1"
18
b11000 A
b10100100 B
#328
0"
08
#329
1"
18
b11001 A
b10100101 B
#330
0"
08
#331
1"
18
b11010 A
b10100110 B
#332
0"
08
#333
1"
18
b11011 A
b10100111 B
#334
0"
08
#335
1"
18
b0 A
b10101000 B
1:
#336
0"
08
#337
1"
18
b1 A
b10101001 B
0:
#338
0"
08
#339
1"
18
b10 A
b10101010 B
#340
0"
08
#341
1"
18
b11 A
b10101011 B
#342
0"
08
#343
1"
18
b100 A
b10101100 B
#344
0"
08
#345
1"
18
b101 A
b10101101 B
#346
0"
08
#347
1"
18
b110 A
b10101110 B
#348
0"
08
#349
1"
18
b111 A
b10101111 B
#350
0"
08
#351
1"
18
b1000 A
b10110000 B
#352
0"
08
#353
1"
18
b1001 A
b10110001 B
#354
0"
08
#355
1"
18
b1010 A
b10110010 B
#356
0"
08
#357
1"
18
b1011 A
b10110011 B
#358
0"
08
#359
1"
18
b1100 A
b10110100 B
#360
0"
08
#361
1"
18
b1101 A
b10110101 B
#362
0"
08
#363
1"
18
b1110 A
b10110110 B
#364
0"
08
#365
1"
18
b1111 A
b10110111 B
#366
0"
08
#367
1"
18
b10000 A
b10111000 B
#368
0"
08
#369
1"
18
b10001 A
b10111001 B
#370
0"
08
#371
1"
18
b10010 A
b10111010 B
#372
0"
08
#373
1"
18
b10011 A
b10111011 B
#374
0"
08
#375
1"
18
b10100 A
b10111100 B
#376
0"
08
#377
1"
18
b10101 A
b10111101 B
#378
0"
08
#379
1"
18
b10110 A
b10111110 B
#380
0"
08
#381
1"
18
b10111 A
b10111111 B
#382
0"
08
#383
1"
18
b11000 A
b11000000 B
#384
0"
08
#385
1"
18
b11001 A
b11000001 B
#386
0"
08
#387
1"
18
b11010 A
b11000010 B
#388
0"
08
#389
1"
18
b11011 A
b11000011 B
#390
0"
08
#391
1"
18
b0 A
b11000100 B
1:
#392
0"
08
#393
1"
18
b1 A
b11000101 B
0:
#394
0"
08
#395
1"
18
b10 A
b11000110 B
#396
0"
08
#397
1"
18
b11 A
b11000111 B
#398
0"
08
#399
1"
18
b100 A
b11001000 B
#400
0"
08
#401
1"
18
b101 A
b11001001 B
#402
0"
08
#403
1"
18
b110 A
b11001010 B
#404
0"
08
#405
1"
18
b111 A
b11001011 B
#406
0"
08
#407
1"
18
b1000 A
b11001100 B
#408
0"
08
#409
1"
18
b1001 A
b11001101 B
#410
0"
08
#411
1"
18
b1010 A
b11001110 B
#412
0"
08
#413
1"
18
b1011 A
b11001111 B
#414
0"
08
#415
1"
18
b1100 A
b11010000 B
#416
0"
08
#417
1"
18
b1101 A
b11010001 B
#418
0"
08
#419
1"
18
b1110 A
b11010010 B
#420
0"
08
#421
1"
18
b1111 A
b11010011 B
#422
0"
08
#423
1"
18
b10000 A
b11010100 B
#424
0"
08
#425
1"
18
b10001 A
b11010101 B
#426
0"
08
#427
1"
18
b10010 A
b11010110 B
#428
0"
08
#429
1"
18
b10011 A
b11010111 B
#430
0"
08
#431
1"
18
b10100 A
b11011000 B
#432
0"
08
#433
1"
18
b10101 A
b11011001 B
#434
0"
08
#435
1"
18
b10110 A
b11011010 B
#436
0"
08
#437
1"
18
b10111 A
b11011011 B
#438
0"
08
#439
1"
18
b11000 A
b11011100 B
#440
0"
08
#441
1"
18
b11001 A
b11011101 B
#442
0"
08
#443
1"
18
b11010 A
b11011110 B
#444
0"
08
#445
1"
18
b11011 A
b11011111 B
#446
0"
08
#447
1"
18
b0 A
b11100000 B
1:
#448
0"
08
#449
1"
18
b1 A
b11100001 B
0:
#450
0"
08
#451
1"
18
b10 A
b11100010 B
#452
0"
08
#453
1"
18
b11 A
b11100011 B
#454
0"
08
#455
1"
18
b100 A
b11100100 B
#456
0"
08
#457
1"
18
b101 A
b11100101 B
#458
0"
08
#459
1"
18
b110 A
b11100110 B
#460
0"
08
#461
1"
18
b111 A
b11100111 B
#462
0"
08
#463
1"
18
b1000 A
b11101000 B
#464
0"
08
#465
1"
18
b1001 A
b11101001 B
#466
0"
08
#467
1"
18
b1010 A
b11101010 B
#468
0"
08
#469
1"
18
b1011 A
b11101011 B
#470
0"
08
#471
1"
18
b1100 A
b11101100 B
#472
0"
08
#473
1"
18
b1101 A
b11101101 B
#474
0"
08
#475
1"
18
b1110 A
b11101110 B
#476
0"
08
#477
1"
18
b1111 A
b11101111 B
#478
0"
08
#479
1"
18
b10000 A
b11110000 B
#480
0"
08
#481
1"
18
b10001 A
b11110001 B
#482
0"
08
#483
1"
18
b10010 A
b11110010 B
#484
0"
08
#485
1"
18
b10011 A
b11110011 B
#486
0"
08
#487
1"
18
b10100 A
b11110100 B
#488
0"
08
#489
1"
18
b10101 A
b11110101 B
#490
0"
08
#491
1"
18
b10110 A
b11110110 B
#492
0"
08
#493
1"
18
b10111 A
b11110111 B
#494
0"
08
#495
1"
18
b11000 A
b11111000 B
#496
0"
08
#497
1"
18
b11001 A
b11111001 B
#498
0"
08
#499
1"
18
b11010 A
b11111010 B
#500
0"
08
#501
1"
18
b11011 A
b11111011 B
#502
0"
08
#503
1"
18
b0 A
b11111100 B
1:
#504
0"
08
#505
1"
18
b1 A
b11111101 B
0:
#506
0"
08
#507
1"
18
b10 A
b11111110 B
#508
0"
08
#509
1"
18
b11 A
b11111111 B
#510
0"
08
#511
1"
18
b100 A
b100000000 B
#512
0"
08
#513
1"
18
b101 A
b100000001 B
#514
0"
08
#515
1"
18
b110 A
b100000010 B
#516
0"
08
#517
1"
18
b111 A
b100000011 B
#518
0"
08
#519
1"
18
b1000 A
b100000100 B
#520
0"
08
#521
1"
18
b1001 A
b100000101 B
#522
0"
08
#523
1"
18
b1010 A
b100000110 B
#524
0"
08
#525
1"
18
b1011 A
b100000111 B
#526
0"
08
#527
1"
18
b1100 A
b100001000 B
#528
0"
08
#529
1"
18
b1101 A
b100001001 B
#530
0"
08
#531
1"
18
b1110 A
b100001010 B
#532
0"
08
#533
1"
18
b1111 A
b100001011 B
#534
0"
08
#535
1"
18
b10000 A
b100001100 B
#536
0"
08
#537
1"
18
b10001 A
b100001101 B
#538
0"
08
#539
1"
18
b10010 A
b100001110 B
#540
0"
08
#541
1"
18
b10011 A
b100001111 B
#542
0"
08
#543
1"
18
b10100 A
b100010000 B
#544
0"
08
#545
1"
18
b10101 A
b100010001 B
#546
0"
08
#547
1"
18
b10110 A
b100010010 B
#548
0"
08
#549
1"
18
b10111 A
b100010011 B
#550
0"
08
#551
1"
18
b11000 A
b100010100 B
#552
0"
08
#553
1"
18
b11001 A
b100010101 B
#554
0"
08
#555
1"
18
b11010 A
b100010110 B
#556
0"
08
#557
1"
18
b11011 A
b100010111 B
#558
0"
08
#559
1"
18
b0 A
b100011000 B
1:
#560
0"
08
#561
1"
18
b1 A
b100011001 B
0:
#562
0"
08
#563
1"
18
b10 A
b100011010 B
#564
0"
08
#565
1"
18
b11 A
b100011011 B
#566
0"
08
#567
1"
18
b100 A
b100011100 B
#568
0"
08
#569
1"
18
b101 A
b100011101 B
#570
0"
08
#571
1"
18
b110 A
b100011110 B
#572
0"
08
#573
1"
18
b111 A
b100011111 B
#574
0"
08
#575
1"
18
b1000 A
b100100000 B
#576
0"
08
#577
1"
18
b1001 A
b100100001 B
#578
0"
08
#579
1"
18
b1010 A
b100100010 B
#580
0"
08
#581
1"
18
b1011 A
b100100011 B
#582
0"
08
#583
1"
18
b1100 A
b100100100 B
#584
0"
08
#585
1"
18
b1101 A
b100100101 B
#586
0"
08
#587
1"
18
b1110 A
b100100110 B
#588
0"
08
#589
1"
18
b1111 A
b100100111 B
#590
0"
08
#591
1"
18
b10000 A
b100101000 B
#592
0"
08
#593
1"
18
b10001 A
b100101001 B
#594
0"
08
#595
1"
18
b10010 A
b100101010 B
#596
0"
08
#597
1"
18
b10011 A
b100101011 B
#598
0"
08
#599
1"
18
b10100 A
b100101100 B
#600
0"
08
#601
1"
18
b10101 A
b100101101 B
#602
0"
08
#603
1"
18
b10110 A
b100101110 B
#604
0"
08
#605
1"
18
b10111 A
b100101111 B
#606
0"
08
#607
1"
18
b11000 A
b100110000 B
#608
0"
08
#609
1"
18
b11001 A
b100110001 B
#610
0"
08
#611
1"
18
b11010 A
b100110010 B
#612
0"
08
#613
1"
18
b11011 A
b100110011 B
#614
0"
08
#615
1"
18
b0 A
b100110100 B
1:
#616
0"
08
#617
1"
18
b1 A
b100110101 B
0:
#618
0"
08
#619
1"
18
b10 A
b100110110 B
#620
0"
08
#621
1"
18
b11 A
b100110111 B
#622
0"
08
#623
1"
18
b100 A
b100111000 B
#624
0"
08
#625
1"
18
b101 A
b100111001 B
#626
0"
08
#627
1"
18
b110 A
b100111010 B
#628
0"
08
#629
1"
18
b111 A
b100111011 B
#630
0"
08
#631
1"
18
b1000 A
b100111100 B
#632
0"
08
#633
1"
18
b1001 A
b100111101 B
#634
0"
08
#635
1"
18
b1010 A
b100111110 B
#636
0"
08
#637
1"
18
b1011 A
b100111111 B
#638
0"
08
#639
1"
18
b1100 A
b101000000 B
#640
0"
08
#641
1"
18
b1101 A
b101000001 B
#642
0"
08
#643
1"
18
b1110 A
b101000010 B
#644
0"
08
#645
1"
18
b1111 A
b101000011 B
#646
0"
08
#647
1"
18
b10000 A
b101000100 B
#648
0"
08
#649
1"
18
b10001 A
b101000101 B
#650
0"
08
#651
1"
18
b10010 A
b101000110 B
#652
0"
08
#653
1"
18
b10011 A
b101000111 B
#654
0"
08
#655
1"
18
b10100 A
b101001000 B
#656
0"
08
#657
1"
18
b10101 A
b101001001 B
#658
0"
08
#659
1"
18
b10110 A
b101001010 B
#660
0"
08
#661
1"
18
b10111 A
b101001011 B
#662
0"
08
#663
1"
18
b11000 A
b101001100 B
#664
0"
08
#665
1"
18
b11001 A
b101001101 B
#666
0"
08
#667
1"
18
b11010 A
b101001110 B
#668
0"
08
#669
1"
18
b11011 A
b101001111 B
#670
0"
08
#671
1"
18
b0 A
b101010000 B
1:
#672
0"
08
#673
1"
18
b1 A
b101010001 B
0:
#674
0"
08
#675
1"
18
b10 A
b101010010 B
#676
0"
08
#677
1"
18
b11 A
b101010011 B
#678
0"
08
#679
1"
18
b100 A
b101010100 B
#680
0"
08
#681
1"
18
b101 A
b101010101 B
#682
0"
08
#683
1"
18
b110 A
b101010110 B
#684
0"
08
#685
1"
18
b111 A
b101010111 B
#686
0"
08
#687
1"
18
b1000 A
b101011000 B
#688
0"
08
#689
1"
18
b1001 A
b101011001 B
#690
0"
08
#691
1"
18
b1010 A
b101011010 B
#692
0"
08
#693
1"
18
b1011 A
b101011011 B
#694
0"
08
#695
1"
18
b1100 A
b101011100 B
#696
0"
08
#697
1"
18
b1101 A
b101011101 B
#698
0"
08
#699
1"
18
b1110 A
b101011110 B
#700
0"
08
#701
1"
18
b1111 A
b101011111 B
#702
0"
08
#703
1"
18
b10000 A
b101100000 B
#704
0"
08
#705
1"
18
b10001 A
b101100001 B
#706
0"
08
#707
1"
18
b10010 A
b101100010 B
#708
0"
08
#709
1"
18
b10011 A
b101100011 B
#710
0"
08
#711
1"
18
b10100 A
b101100100 B
#712
0"
08
#713
1"
18
b10101 A
b101100101 B
#714
0"
08
#715
1"
18
b10110 A
b101100110 B
#716
0"
08
#717
1"
18
b10111 A
b101100111 B
#718
0"
08
#719
1"
18
b11000 A
b101101000 B
#720
0"
08
#721
1"
18
b11001 A
b101101001 B
#722
0"
08
